jaguarcrypto/__init__.py
jaguarcrypto/jaguarEncryptor.py
jaguarcrypto-3.4.6.2.dist-info/LICENSE
jaguarcrypto-3.4.6.2.dist-info/METADATA
jaguarcrypto-3.4.6.2.dist-info/WHEEL
jaguarcrypto-3.4.6.2.dist-info/top_level.txt
jaguarcrypto-3.4.6.2.dist-info/RECORD
