Metadata-Version: 2.1
Name: jaguarcrypto
Version: 3.4.6.2
Summary: Encryption/decryption library compatible with JaguarDB
Home-page: https://github.com/fserv/jaguar-sdk/encryption/python/jaguarcrypto
Author: DataJaguar, Inc.
License: BSD-3-Clause
Platform: UNKNOWN
Classifier: Programming Language :: Python :: 3
Classifier: License :: OSI Approved :: BSD License
Classifier: Operating System :: OS Independent
Requires-Python: >=3.6
License-File: LICENSE
Requires-Dist: cryptography (>=41.0.0)
